oslg/__init__.py
oslg/oslg.py
oslg-0.4.0.dist-info/licenses/LICENSE
oslg-0.4.0.dist-info/METADATA
oslg-0.4.0.dist-info/WHEEL
oslg-0.4.0.dist-info/top_level.txt
oslg-0.4.0.dist-info/RECORD
