Metadata-Version: 2.4
Name: oslg
Version: 0.4.0
Summary: OpenStudio SDK logger for Python
Author-email: Denis Bourgeois <denis@rd2.ca>
Maintainer-email: Denis Bourgeois <denis@rd2.ca>
License-Expression: BSD-3-Clause
Project-URL: Homepage, https://github.com/rd2/pyOSlg
Project-URL: Bug Tracker, https://github.com/rd2/pyOSlg/issues
Keywords: openstudio,logger
Classifier: Programming Language :: Python :: 3.2
Classifier: Intended Audience :: Developers
Classifier: Topic :: Software Development :: Libraries :: Python Modules
Classifier: Operating System :: OS Independent
Requires-Python: >=3.2
License-File: LICENSE
Dynamic: license-file
